CHANGES.txt
DEPENDENCES.txt
README.txt
setup.py
src/ng/__init__.py
src/ng.app.photo.egg-info/PKG-INFO
src/ng.app.photo.egg-info/SOURCES.txt
src/ng.app.photo.egg-info/dependency_links.txt
src/ng.app.photo.egg-info/namespace_packages.txt
src/ng.app.photo.egg-info/not-zip-safe
src/ng.app.photo.egg-info/requires.txt
src/ng.app.photo.egg-info/top_level.txt
src/ng/app/__init__.py
src/ng/app/photo/__init__.py
src/ng/app/photo/configure.zcml
src/ng/app/photo/interfaces.py
src/ng/app/photo/ng.app.photo.txt
src/ng/app/photo/photo.py
src/ng/app/photo/phototoolfiltersvocabulary.py
src/ng/app/photo/phototools.py
src/ng/app/photo/browser/__init__.py
src/ng/app/photo/browser/configure.zcml
src/ng/app/photo/browser/editphoto.pt
src/ng/app/photo/browser/editphoto.py
src/ng/app/photo/browser/photoadapter.py
src/ng/app/photo/browser/widgets.py
src/ng/app/photo/etc/ng.app.photo-configure.zcml
